bottle_rest_serializer/__init__.py
bottle_rest_serializer-0.1.4.dist-info/LICENSE
bottle_rest_serializer-0.1.4.dist-info/METADATA
bottle_rest_serializer-0.1.4.dist-info/WHEEL
bottle_rest_serializer-0.1.4.dist-info/top_level.txt
bottle_rest_serializer-0.1.4.dist-info/RECORD
