Metadata-Version: 2.1
Name: bottle-rest-serializer
Version: 0.1.4
Summary: JSON serializer suited for REST apis developed with BottlePy
Home-page: https://github.com/truckpad/bottle_rest_serializer-rest-serializer
Author: Marcos Araujo Sobrinho
Author-email: marcos.sobrinho@truckpad.com.br
License: UNKNOWN
Platform: UNKNOWN
Classifier: Development Status :: 2 - Pre-Alpha
Classifier: Operating System :: POSIX
Classifier: Programming Language :: Python :: 3
Classifier: Topic :: Internet :: WWW/HTTP
Requires-Dist: bottle
